discogs2xlsx/__init__.py
discogs2xlsx/__init__.pyi
discogs2xlsx/__main__.py
discogs2xlsx/_discogs.py
discogs2xlsx/_discogs.pyi
discogs2xlsx/_logger.py
discogs2xlsx/_logger.pyi
discogs2xlsx/_options.py
discogs2xlsx/_options.pyi
discogs2xlsx/_xlsx.py
discogs2xlsx/_xlsx.pyi
discogs2xlsx/py.typed
discogs2xlsx-0.4.0.dist-info/LICENSE
discogs2xlsx-0.4.0.dist-info/METADATA
discogs2xlsx-0.4.0.dist-info/WHEEL
discogs2xlsx-0.4.0.dist-info/entry_points.txt
discogs2xlsx-0.4.0.dist-info/top_level.txt
discogs2xlsx-0.4.0.dist-info/RECORD
