Metadata-Version: 2.1
Name: discogs2xlsx
Version: 0.4.0
Summary: Exports your Discogs collection or wantlist into a xlsx file.
Home-page: https://github.com/fscm/discogs2xlsx
Author: Frederico Martins
License: MIT
Project-URL: Documentation, http://fscm.github.io/discogs2xlsx
Project-URL: Source, https://github.com/fscm/discogs2xlsx
Keywords: discogs,xlsx
Platform: UNKNOWN
Classifier: Development Status :: 4 - Beta
Classifier: Environment :: Console
Classifier: Intended Audience :: End Users/Desktop
Classifier: License :: OSI Approved :: MIT License
Classifier: Operating System :: OS Independent
Classifier: Programming Language :: Python :: 3.9
Classifier: Programming Language :: Python :: 3.10
Classifier: Topic :: Utilities
Classifier: Typing :: Typed
Requires-Python: >=3.9, <4
License-File: LICENSE
Requires-Dist: progress (>=1.5)
Requires-Dist: requests (>=2.25.1)
Requires-Dist: xlsxwriter (>=3.0.0)
